LICENSE
MANIFEST.in
README.rst
requirements.txt
setup.cfg
setup.py
python_roku_custom.egg-info/PKG-INFO
python_roku_custom.egg-info/SOURCES.txt
python_roku_custom.egg-info/dependency_links.txt
python_roku_custom.egg-info/requires.txt
python_roku_custom.egg-info/top_level.txt
roku/__init__.py
roku/core.py
roku/discovery.py
roku/proxy.py
roku/server.py
roku/tests.py
roku/emulator/__init__.py
roku/emulator/core.py